arpx/__init__.py
arpx/bridge.py
arpx/certs.py
arpx/cli.py
arpx/compose.py
arpx/dns.py
arpx/mdns.py
arpx/network.py
arpx/proxy.py
arpx/server.py
arpx/terminator.py
arpx/utils.py
LICENSE
NOTICE
arpx-0.0.21.dist-info/METADATA
arpx-0.0.21.dist-info/WHEEL
arpx-0.0.21.dist-info/entry_points.txt
arpx-0.0.21.dist-info/licenses/LICENSE
arpx-0.0.21.dist-info/licenses/NOTICE
arpx-0.0.21.dist-info/RECORD
