Metadata-Version: 2.4
Name: arpx
Version: 0.0.21
Summary: Dynamic multi-IP LAN HTTP/HTTPS server manager with ARP visibility
Project-URL: Homepage, https://github.com/dynapsys/arpx
Project-URL: Issues, https://github.com/dynapsys/arpx/issues
Author-email: Tom Sapletta <info@softreck.dev>
License:                                  Apache License
License-File: LICENSE
License-File: NOTICE
Keywords: arp,certificates,http,https,lan,lets-encrypt,mkcert,network
Classifier: Development Status :: 3 - Alpha
Classifier: License :: OSI Approved :: Apache Software License
Classifier: Operating System :: POSIX :: Linux
Classifier: Programming Language :: Python :: 3
Classifier: Topic :: Internet
Classifier: Topic :: System :: Networking
Requires-Python: >=3.8
Requires-Dist: cryptography>=41.0
Provides-Extra: compose
Requires-Dist: pyyaml>=6.0; extra == 'compose'
Provides-Extra: le
Requires-Dist: certbot>=2.9.0; extra == 'le'
Provides-Extra: mdns
Requires-Dist: zeroconf>=0.37.0; extra == 'mdns'
Provides-Extra: test
Requires-Dist: pytest-timeout>=2.1; extra == 'test'
Requires-Dist: pytest>=7.0; extra == 'test'
